{"_id":"@emmetio/math-expression","_rev":"3-408676dd806632891dc55960edf1f870","name":"@emmetio/math-expression","description":"Parse &amp; evaluate simple math expressions","dist-tags":{"latest":"0.1.1"},"versions":{"0.1.0":{"name":"@emmetio/math-expression","version":"0.1.0","description":"Parse &amp; evaluate simple math expressions","main":"dist/math.cjs.js","module":"dist/math.es.js","scripts":{"test":"mocha","build":"rollup -c","watch":"rollup -wc"},"repository":{"type":"git","url":"git+https://github.com/emmetio/math-expression.git"},"keywords":[],"author":{"name":"Sergey Chikuyonok","email":"serge.che@gmail.com"},"license":"ISC","bugs":{"url":"https://github.com/emmetio/math-expression/issues"},"homepage":"https://github.com/emmetio/math-expression#readme","dependencies":{"@emmetio/stream-reader":"^2.0.1","@emmetio/stream-reader-utils":"^0.1.0"},"devDependencies":{"babel-plugin-transform-es2015-modules-commonjs":"^6.24.1","babel-register":"^6.24.1","mocha":"^3.2.0","rollup":"^0.41.6","rollup-watch":"^3.2.2"},"gitHead":"f17789edce0d12dc4bf8439f8aab137105ccc0e9","_id":"@emmetio/math-expression@0.1.0","_shasum":"cfe8c03b70a61cc7e42193e90252dc077504d6db","_from":".","_npmVersion":"4.1.2","_nodeVersion":"7.7.3","_npmUser":{"name":"emmetio","email":"info@emmet.io"},"dist":{"shasum":"cfe8c03b70a61cc7e42193e90252dc077504d6db","tarball":"https://registry.npmjs.org/@emmetio/math-expression/-/math-expression-0.1.0.tgz"},"maintainers":[{"name":"emmetio","email":"info@emmet.io"}],"_npmOperationalInternal":{"host":"packages-18-east.internal.npmjs.com","tmp":"tmp/math-expression-0.1.0.tgz_1492036690965_0.04797977930866182"},"directories":{}},"0.1.1":{"name":"@emmetio/math-expression","version":"0.1.1","description":"Parse &amp; evaluate simple math expressions","main":"dist/math.cjs.js","module":"dist/math.es.js","scripts":{"test":"mocha","build":"rollup -c","watch":"rollup -wc","prepublish":"npm run test && npm run build"},"repository":{"type":"git","url":"git+https://github.com/emmetio/math-expression.git"},"keywords":[],"author":{"name":"Sergey Chikuyonok","email":"serge.che@gmail.com"},"license":"ISC","bugs":{"url":"https://github.com/emmetio/math-expression/issues"},"homepage":"https://github.com/emmetio/math-expression#readme","dependencies":{"@emmetio/stream-reader":"^2.0.1","@emmetio/stream-reader-utils":"^0.1.0"},"devDependencies":{"babel-plugin-transform-es2015-modules-commonjs":"^6.24.1","babel-register":"^6.24.1","mocha":"^3.2.0","rollup":"^0.41.6","rollup-watch":"^3.2.2"},"gitHead":"31dc028f80c27b5b00be9395e35ebd07c9cd8862","_id":"@emmetio/math-expression@0.1.1","_shasum":"1ff2c7f05800f64c57ca89038ee18bce9f5776dc","_from":".","_npmVersion":"4.1.2","_nodeVersion":"7.7.3","_npmUser":{"name":"emmetio","email":"info@emmet.io"},"dist":{"shasum":"1ff2c7f05800f64c57ca89038ee18bce9f5776dc","tarball":"https://registry.npmjs.org/@emmetio/math-expression/-/math-expression-0.1.1.tgz"},"maintainers":[{"name":"emmetio","email":"info@emmet.io"}],"_npmOperationalInternal":{"host":"packages-18-east.internal.npmjs.com","tmp":"tmp/math-expression-0.1.1.tgz_1492119798667_0.8933299670461565"},"directories":{}}},"readme":"# math-expression\nParse &amp; evaluate simple math expressions\n","maintainers":[{"name":"emmetio","email":"info@emmet.io"}],"time":{"modified":"2017-04-20T21:06:49.156Z","created":"2017-04-12T22:38:11.550Z","0.1.0":"2017-04-12T22:38:11.550Z","0.1.1":"2017-04-13T21:43:19.334Z"},"homepage":"https://github.com/emmetio/math-expression#readme","keywords":[],"repository":{"type":"git","url":"git+https://github.com/emmetio/math-expression.git"},"author":{"name":"Sergey Chikuyonok","email":"serge.che@gmail.com"},"bugs":{"url":"https://github.com/emmetio/math-expression/issues"},"license":"ISC","readmeFilename":"README.md","_attachments":{},"_etag":"W/\"58f922e9-edd\"","_lastModified":"Thu, 20 Apr 2017 21:06:49 GMT","_cached":true}